streamlit_eidos/__init__.py
streamlit_eidos/frontend/.eslintrc.cjs
streamlit_eidos/frontend/.gitignore
streamlit_eidos/frontend/README.md
streamlit_eidos/frontend/index.html
streamlit_eidos/frontend/package-lock.json
streamlit_eidos/frontend/package.json
streamlit_eidos/frontend/vite.config.js
streamlit_eidos/frontend/dist/index.html
streamlit_eidos/frontend/dist/assets/index-Sp77uM4B.js
streamlit_eidos/frontend/src/Component.jsx
streamlit_eidos/frontend/src/main.jsx
streamlit_eidos-0.2.0.dist-info/LICENSE
streamlit_eidos-0.2.0.dist-info/METADATA
streamlit_eidos-0.2.0.dist-info/WHEEL
streamlit_eidos-0.2.0.dist-info/top_level.txt
streamlit_eidos-0.2.0.dist-info/RECORD
